glenoidplanefitting/__init__.py
glenoidplanefitting/__main__.py
glenoidplanefitting/_version.py
glenoidplanefitting/algorithms/__init__.py
glenoidplanefitting/algorithms/colour_palette.py
glenoidplanefitting/algorithms/friedman.py
glenoidplanefitting/algorithms/models.py
glenoidplanefitting/algorithms/plane_fitting.py
glenoidplanefitting/algorithms/vault.py
glenoidplanefitting/ui/__init__.py
glenoidplanefitting/ui/glenoidplanefitting_command_line.py
glenoidplanefitting/ui/glenoidplanefitting_demo.py
glenoidplanefitting/widgets/__init__.py
glenoidplanefitting/widgets/visualisation.py
tests/algorithms/__init__.py
tests/algorithms/test_freidman.py
tests/algorithms/test_models.py
tests/algorithms/test_plane_fitting.py
tests/algorithms/test_vault.py
glenoidplanefitting-0.0.3.dist-info/LICENSE
glenoidplanefitting-0.0.3.dist-info/METADATA
glenoidplanefitting-0.0.3.dist-info/WHEEL
glenoidplanefitting-0.0.3.dist-info/entry_points.txt
glenoidplanefitting-0.0.3.dist-info/top_level.txt
glenoidplanefitting-0.0.3.dist-info/RECORD
