Metadata-Version: 2.1
Name: glenoidplanefitting
Version: 0.0.3
Summary: implements a plane fitting algorithm to read a vtk polydata file and outputs fitted plane
Home-page: https://github.com/SciKit-Surgery/glenoidplanefitting
Author: Asta Olafsdottir
Author-email: YOUR-EMAIL@ucl.ac.uk
License: BSD-3 license
Keywords: medical imaging
Platform: UNKNOWN
Classifier: Development Status :: 3 - Alpha
Classifier: Intended Audience :: Developers
Classifier: Intended Audience :: Healthcare Industry
Classifier: Intended Audience :: Information Technology
Classifier: Intended Audience :: Science/Research
Classifier: License :: OSI Approved :: BSD License
Classifier: Programming Language :: Python
Classifier: Programming Language :: Python :: 2
Classifier: Programming Language :: Python :: 3
Classifier: Topic :: Scientific/Engineering :: Information Analysis
Classifier: Topic :: Scientific/Engineering :: Medical Science Apps.
Requires-Dist: numpy
Requires-Dist: vtk
Requires-Dist: scikit-surgeryvtk
Requires-Dist: scikit-surgerycore
